MANIFEST.in
README.md
setup.cfg
setup.py
tenyksservice/__init__.py
tenyksservice/config.py
tenyksservice/context.py
tenyksservice/filters.py
tenyksservice/module_loader.py
tenyksservice/service.py
tenyksservice/settings.py.dist
tenyksservice.egg-info/PKG-INFO
tenyksservice.egg-info/SOURCES.txt
tenyksservice.egg-info/dependency_links.txt
tenyksservice.egg-info/entry_points.txt
tenyksservice.egg-info/not-zip-safe
tenyksservice.egg-info/requires.txt
tenyksservice.egg-info/top_level.txt
tenyksservice/packages/__init__.py
tenyksservice/packages/six.py
tenyksservice/packages/termcolor.py