Metadata-Version: 1.0
Name: tenyksservice
Version: 2.2.0
Summary: Tenyks service class for making fun things for Tenyks.
Home-page: https://github.com/kyleterry/tenyks-service
Author: Kyle Terry
Author-email: kyle@kyleterry.com
License: LICENSE
Keywords: irc bot zeromq service
Platform: UNKNOWN
